{"_path":"/tour_bashkortostan","_dir":{"_path":"/tour_bashkortostan/_dir","layout":"post","title":"Dir"},"_draft":false,"_partial":false,"_locale":"","title":"Маршруты по Башкирии","description":"Read the best articles related to the directory.","layout":"wide","body":{"type":"root","children":[{"type":"element","tag":"h1","props":{"id":"маршруты-по-башкирии"},"children":[{"type":"text","value":"Маршруты по Башкирии"}]},{"type":"element","tag":"bashkortostan-tours-grid","props":{},"children":[]}],"toc":{"title":"","searchDepth":2,"depth":2,"links":[]}},"_type":"markdown","_id":"content:tour_bashkortostan.md","_source":"content","_file":"tour_bashkortostan.md","_stem":"tour_bashkortostan","_extension":"md","sitemap":{"loc":"/tour_bashkortostan"}}